Giraffe_View/__init__.py
Giraffe_View/estimated_read_accuracy.py
Giraffe_View/function.py
Giraffe_View/gc_bias.py
Giraffe_View/homopolymer.py
Giraffe_View/observed_read_accuracy.py
Giraffe_View/plot.py
Giraffe_View/regional_modification.py
Giraffe_View/summary_html.py
Giraffe_View-0.2.3.data/scripts/giraffe
Giraffe_View-0.2.3.data/scripts/giraffe_plot
Giraffe_View-0.2.3.data/scripts/giraffe_run_demo
Giraffe_View-0.2.3.data/scripts/homopolymer_count
Giraffe_View-0.2.3.data/scripts/renormalization_sequencing_bias
Giraffe_View-0.2.3.dist-info/LICENSE
Giraffe_View-0.2.3.dist-info/METADATA
Giraffe_View-0.2.3.dist-info/WHEEL
Giraffe_View-0.2.3.dist-info/top_level.txt
Giraffe_View-0.2.3.dist-info/RECORD
